mayafbx/__init__.py
mayafbx/bases.py
mayafbx/enums.py
mayafbx/exceptions.py
mayafbx/exporter.py
mayafbx/importer.py
mayafbx/utils.py
mayafbx-1.0.0.dist-info/METADATA
mayafbx-1.0.0.dist-info/WHEEL
mayafbx-1.0.0.dist-info/licenses/LICENSE
mayafbx-1.0.0.dist-info/RECORD
