Metadata-Version: 2.3
Name: mayafbx
Version: 1.0.0
Summary: Python wrapper for Autodesk Maya FBX plugin
Project-URL: Github, https://github.com/tahv/mayafbx
Project-URL: Changelog, https://mayafbx.readthedocs.io/latest/changelog.html
Project-URL: Documentation, https://mayafbx.readthedocs.io/latest
Author: Thibaud Gambier
License-Expression: MIT
License-File: LICENSE
Keywords: fbx,maya
Classifier: Development Status :: 4 - Beta
Classifier: License :: OSI Approved :: MIT License
Classifier: Programming Language :: Python :: 3.7
Classifier: Programming Language :: Python :: 3.8
Classifier: Programming Language :: Python :: 3.9
Classifier: Programming Language :: Python :: 3.10
Classifier: Programming Language :: Python :: 3.11
Classifier: Programming Language :: Python :: 3.12
Classifier: Programming Language :: Python :: Implementation :: CPython
Requires-Python: >=3.7
Provides-Extra: build
Requires-Dist: hatch; extra == 'build'
Provides-Extra: dev
Requires-Dist: coverage; extra == 'dev'
Requires-Dist: furo; extra == 'dev'
Requires-Dist: hatch; extra == 'dev'
Requires-Dist: mypy; extra == 'dev'
Requires-Dist: myst-parser; extra == 'dev'
Requires-Dist: pytest; extra == 'dev'
Requires-Dist: ruff; extra == 'dev'
Requires-Dist: sphinx; extra == 'dev'
Requires-Dist: sphinx-autobuild; extra == 'dev'
Requires-Dist: sphinx-toolbox; extra == 'dev'
Provides-Extra: docs
Requires-Dist: furo; extra == 'docs'
Requires-Dist: myst-parser; extra == 'docs'
Requires-Dist: sphinx; extra == 'docs'
Requires-Dist: sphinx-toolbox; extra == 'docs'
Provides-Extra: mypy
Requires-Dist: mypy; extra == 'mypy'
Requires-Dist: pytest; extra == 'mypy'
Provides-Extra: style
Requires-Dist: ruff; extra == 'style'
Provides-Extra: tests
Requires-Dist: coverage; extra == 'tests'
Requires-Dist: pytest; extra == 'tests'
